AUTHORS.rst
CONTRIBUTING.rst
HISTORY.rst
LICENSE
MANIFEST.in
README.rst
setup.cfg
setup.py
docs/Makefile
docs/authors.rst
docs/conf.py
docs/contributing.rst
docs/history.rst
docs/index.rst
docs/installation.rst
docs/make.bat
docs/readme.rst
docs/usage.rst
dyna_settings/__init__.py
dyna_settings/core.py
dyna_settings.egg-info/PKG-INFO
dyna_settings.egg-info/SOURCES.txt
dyna_settings.egg-info/dependency_links.txt
dyna_settings.egg-info/not-zip-safe
dyna_settings.egg-info/pbr.json
dyna_settings.egg-info/top_level.txt
tests/__init__.py
tests/test_dyna_settings.py