Metadata-Version: 1.1
Name: dyna-settings
Version: 0.1.1
Summary: Dynamic project settings to automatically switch settings by environment detection.
Home-page: https://github.com/curtisforrester/dyna_settings
Author: Curtis Forrester
Author-email: curtis@bredbeddle.net
License: BSD
Keywords: dyna_settings
Platform: UNKNOWN
Classifier: Development Status :: 2 - Pre-Alpha
Classifier: Intended Audience :: Developers
Classifier: License :: OSI Approved :: BSD License
Classifier: Natural Language :: English
Classifier: Programming Language :: Python :: 2
Classifier: Programming Language :: Python :: 2.7
